orionpy/__init__.py
orionpy/orioncore/Elements.py
orionpy/orioncore/Exceptions.py
orionpy/orioncore/Filter.py
orionpy/orioncore/Filters.py
orionpy/orioncore/Group.py
orionpy/orioncore/Groups.py
orionpy/orioncore/Orion.py
orionpy/orioncore/OrionBase.py
orionpy/orioncore/OrionRest.py
orionpy/orioncore/RequestManager.py
orionpy/orioncore/Subject.py
orionpy/orioncore/Subjects.py
orionpy/orioncore/UrlBuilder.py
orionpy/orioncore/User.py
orionpy/orioncore/Users.py
orionpy/orioncore/WebmapPermissionsCalculator.py
orionpy/orioncore/__init__.py
orionpy/orioncore/cfg_global.py
orionpy/orioncore/features/Geonote.py
orionpy/orioncore/features/Geonotes.py
orionpy/orioncore/features/Item.py
orionpy/orioncore/features/Items.py
orionpy/orioncore/features/Project.py
orionpy/orioncore/features/Projects.py
orionpy/orioncore/features/__init__.py
orionpy/orioncore/resources/BusinessResource.py
orionpy/orioncore/resources/Businesses.py
orionpy/orioncore/resources/CadastreResource.py
orionpy/orioncore/resources/Field.py
orionpy/orioncore/resources/Fields.py
orionpy/orioncore/resources/IMCResource.py
orionpy/orioncore/resources/IMCs.py
orionpy/orioncore/resources/Layer.py
orionpy/orioncore/resources/Layers.py
orionpy/orioncore/resources/Resource.py
orionpy/orioncore/resources/Service.py
orionpy/orioncore/resources/Services.py
orionpy/orioncore/resources/StatsResource.py
orionpy/orioncore/resources/StorageResource.py
orionpy/orioncore/resources/Table.py
orionpy/orioncore/resources/Tables.py
orionpy/orioncore/resources/__init__.py
orionpy/orioncsv/__init__.py
orionpy/orioncsv/csvfilteringcadastre.py
orionpy/orioncsv/csvfilteringvalues.py
orionpy/orioncsv/csvorganisationunit.py
orionpy/orioncsv/csvrightsmanagement.py
orionpy/orioncsv/orioncsv.py
orionpy/oriongis/__init__.py
orionpy/oriongis/oriongis.py
orionpy/oriongis/servicegis.py
orionpy/oriongis/servicesgismanager.py
orionpy-24.12.17.dist-info/LICENSE
orionpy-24.12.17.dist-info/METADATA
orionpy-24.12.17.dist-info/WHEEL
orionpy-24.12.17.dist-info/top_level.txt
orionpy-24.12.17.dist-info/RECORD
