Metadata-Version: 2.1
Name: orionpy
Version: 24.12.17
Summary: Python API to administrate arcOpole Builder
Home-page: https://gitlab.com/esrifrance-public/orionpy/orionpy
Author: acollange
Author-email: acollange@esrifrance.fr
License: Proprietary
Keywords: orionpy orion arcopole builder
Classifier: Development Status :: 3 - Alpha
Classifier: Environment :: Console
Classifier: Intended Audience :: Developers
Classifier: Programming Language :: Python :: 3 :: Only
Classifier: License :: Other/Proprietary License
Requires-Python: >=3.7
License-File: LICENSE
Requires-Dist: requests
Requires-Dist: urllib3
